design.v
// Code your design here
module Moore_1101 (
  input clk,
  input A,
  input reset,
  output Out,
  output [2:0] S
);

  reg Out = 0;
  reg [2:0] S = 0;  
  wire [2:0] S_fut=0 ;
  
  wire s01;
  assign s01 = (~S[2]&~S[1]&~S[0]&A);
  
  wire s02=(S[1]&~S[0]&~A);
  wire s03= s01|s02;

  assign S_fut[0] = (~S[2]&~S[1]&~S[0]&A) | (S[1]&~S[0]&~A); //
  assign S_fut[1] = (~S[1]&S[0]&A) | (S[2]&A) | ( S[1] & ~S[0] ); //
  assign S_fut[2] = ( S[1] & S[0] & A);
  
  initial
    begin
      S = 3'b0;
    end
  // en cada flanco a positivo se guarda en los flip flops S[2:0]
  always @ (posedge clk)
    begin
      if (reset)
        begin
          S <= 0;
          $display("reset S=%b \tS fut=%b \tA=%b \tS01=%b \tS02=%b \tS03=%b", S, S_fut, A, s01, s02, s03);
        end
      else
        begin
          S[0] <= S_fut[0]; // (~S[2]&~S[1]&~S[0]&A) | (S[1]&~S[0]&~A);//
          S[1] <= S_fut[1]; //(~S[1]&S[0]&A) | (S[1]&~S[0]) | (S[2]&A); //;
          S[2] <= ( S[1] & S[0] & A);
          // lógica combinacional de la salida
          Out <= S[2];
          $display("S=%b \tS fut=%b \tA=%b", S, S_fut, A);

        end;
    end
  
 //
  
endmodule

testbench.v
//-----------------------------------------------------
// José Eduardo Morales
// Maquina de estados Finitos - Moore
// Cuando lee una cadena 1101 y despliega 1
//-----------------------------------------------------

`include "design.v"

module testbench();
  // entradas y salidas
  reg entrada;
  reg clk, reset;
  wire salida;
  wire [2:0] estado;
  
  // conectamos la maquina de estados
  Moore_1101 FSM (clk, entrada, reset, salida, estado);
  
  // simulación
  initial
    begin
      // calores iniciales
      entrada = 0;
      reset = 1;
      clk = 1;
      // preparar la consola
      $display("\t\t Time \tIn \tOut, \tState");
      $monitor("%d \t%d \t%d \t%b", $time, entrada, salida, estado); 
      // variación de las entradas
      #10 reset = 0;
      #20 entrada = 1;
      #10 entrada = 1;
      #10 entrada = 0;
      #10 entrada = 1;
      #10 entrada = 1;
      #10 entrada = 1;
      reset = 1;
      #10 entrada = 1;
      reset=0;
      #10 entrada = 0;
      #10 entrada = 0;
      #10 entrada = 1;
      #10 entrada = 1;
      #10 entrada = 0;
      #10 entrada = 1;
      #10 entrada = 1;
    end
  
  // tiempo final
  initial 
    #200 $finish;
  // señal de reloj
  always
    #5 clk = ~clk;
  
  // señales
  initial 
    begin
  	  $dumpfile("dump.vcd");
  	  $dumpvars(1);
    end
endmodule

dump.vcd
$date
	Thu Apr 25 11:34:38 2019
$end
$version
	Icarus Verilog
$end
$timescale
	1s
$end
$scope module testbench $end
$var wire 1 ! salida $end
$var wire 3 " estado [2:0] $end
$var reg 1 # clk $end
$var reg 1 $ entrada $end
$var reg 1 % reset $end
$upscope $end
$enddefinitions $end
#0
$dumpvars
1%
0$
1#
b0 "
0!
$end
#5
0#
#10
1#
0%
#15
0#
#20
1#
#25
0#
#30
1#
1$
#35
0#
#40
b0x "
1#
#45
0#
#50
b0xx "
1#
0$
#55
0#
#60
bx "
1#
1$
#65
0#
#70
x!
1#
#75
0#
#80
b0 "
1#
1%
#85
0#
#90
0!
b0x "
1#
0%
#95
0#
#100
b0xx "
1#
0$
#105
0#
#110
1#
#115
0#
#120
bx "
1#
1$
#125
0#
#130
x!
1#
#135
0#
#140
b0xx "
1#
0$
#145
0#
#150
0!
bx "
1#
1$
#155
0#
#160
x!
1#
